atomistics/__init__.py
atomistics/_version.py
atomistics/calculators/__init__.py
atomistics/calculators/ase.py
atomistics/calculators/hessian.py
atomistics/calculators/interface.py
atomistics/calculators/qe.py
atomistics/calculators/sphinxdft.py
atomistics/calculators/vasp.py
atomistics/calculators/wrapper.py
atomistics/calculators/lammps/__init__.py
atomistics/calculators/lammps/commands.py
atomistics/calculators/lammps/filecalculator.py
atomistics/calculators/lammps/helpers.py
atomistics/calculators/lammps/libcalculator.py
atomistics/calculators/lammps/phonon.py
atomistics/referencedata/__init__.py
atomistics/referencedata/mendeleev.py
atomistics/referencedata/wikipedia.py
atomistics/referencedata/wolframalpha.py
atomistics/shared/__init__.py
atomistics/shared/import_warning.py
atomistics/shared/output.py
atomistics/shared/parallel.py
atomistics/shared/thermal_expansion.py
atomistics/shared/tqdm_iterator.py
atomistics/workflows/__init__.py
atomistics/workflows/interface.py
atomistics/workflows/langevin.py
atomistics/workflows/molecular_dynamics.py
atomistics/workflows/quasiharmonic.py
atomistics/workflows/structure_optimization.py
atomistics/workflows/elastic/__init__.py
atomistics/workflows/elastic/elastic_moduli.py
atomistics/workflows/elastic/helper.py
atomistics/workflows/elastic/symmetry.py
atomistics/workflows/elastic/workflow.py
atomistics/workflows/evcurve/__init__.py
atomistics/workflows/evcurve/debye.py
atomistics/workflows/evcurve/fit.py
atomistics/workflows/evcurve/helper.py
atomistics/workflows/evcurve/thermo.py
atomistics/workflows/evcurve/workflow.py
atomistics/workflows/phonons/__init__.py
atomistics/workflows/phonons/helper.py
atomistics/workflows/phonons/units.py
atomistics/workflows/phonons/workflow.py
atomistics-0.3.5.dist-info/METADATA
atomistics-0.3.5.dist-info/WHEEL
atomistics-0.3.5.dist-info/licenses/LICENSE
atomistics-0.3.5.dist-info/RECORD
