Metadata-Version: 2.4
Name: atomistics
Version: 0.3.5
Summary: Interfaces for atomistic simulation codes and workflows
Project-URL: Homepage, https://github.com/pyiron/atomistics
Project-URL: Documentation, https://atomistics.readthedocs.io
Project-URL: Repository, https://github.com/pyiron/atomistics
Author-email: Jan Janssen <janssen@mpie.de>
License: BSD 3-Clause License
License-File: LICENSE
Keywords: pyiron
Classifier: Development Status :: 5 - Production/Stable
Classifier: Intended Audience :: Science/Research
Classifier: License :: OSI Approved :: BSD License
Classifier: Operating System :: OS Independent
Classifier: Programming Language :: Python :: 3.9
Classifier: Programming Language :: Python :: 3.10
Classifier: Programming Language :: Python :: 3.11
Classifier: Programming Language :: Python :: 3.12
Classifier: Programming Language :: Python :: 3.13
Classifier: Topic :: Scientific/Engineering :: Physics
Requires-Python: <3.15,>=3.9
Requires-Dist: ase<=3.27.0,>=3.23.0
Requires-Dist: numpy<=2.3.5,>=1.26.4
Requires-Dist: scipy<=1.16.3,>=1.11.2
Requires-Dist: spglib<=2.7.0,>=2.0.2
Provides-Extra: experimental
Requires-Dist: lxml<=6.0.2,>=4.9.1; extra == 'experimental'
Requires-Dist: mendeleev<=1.1.0,>=0.12.0; extra == 'experimental'
Requires-Dist: pandas<=2.3.3,>=2.0.3; extra == 'experimental'
Requires-Dist: requests<=2.32.5,>=2.24.0; extra == 'experimental'
Provides-Extra: gpaw
Requires-Dist: gpaw<=25.7.0,>=21.6.0; extra == 'gpaw'
Provides-Extra: lammps
Requires-Dist: jinja2<=3.1.6,>=2.11.3; extra == 'lammps'
Requires-Dist: pandas<=2.3.3,>=2.0.3; extra == 'lammps'
Requires-Dist: pyiron-lammps<=0.5.2,>=0.3.2; extra == 'lammps'
Requires-Dist: pylammpsmpi<=0.3.8,>=0.2.1; extra == 'lammps'
Provides-Extra: lammps-phonons
Requires-Dist: dynaphopy<=1.18.0,>=1.17.11; extra == 'lammps-phonons'
Requires-Dist: jinja2<=3.1.6,>=2.11.3; extra == 'lammps-phonons'
Requires-Dist: pandas<=2.3.3,>=2.0.3; extra == 'lammps-phonons'
Requires-Dist: pyiron-lammps<=0.5.2,>=0.3.2; extra == 'lammps-phonons'
Requires-Dist: pylammpsmpi<=0.3.8,>=0.2.1; extra == 'lammps-phonons'
Provides-Extra: phonopy
Requires-Dist: phonopy<=2.46.1,>=2.20.0; extra == 'phonopy'
Requires-Dist: seekpath<=2.1.0,>=1.9.0; extra == 'phonopy'
Requires-Dist: structuretoolkit<=0.0.39,>=0.0.10; extra == 'phonopy'
Provides-Extra: qe
Requires-Dist: pwtools==1.3.0; extra == 'qe'
Provides-Extra: sphinxdft
Requires-Dist: sphinx-parser==0.1.6; extra == 'sphinxdft'
Provides-Extra: tqdm
Requires-Dist: tqdm==4.67.1; extra == 'tqdm'
Provides-Extra: vasp
Requires-Dist: pyiron-vasp==0.2.18; extra == 'vasp'
